{"v":"5.9.0","fr":20,"ip":0,"op":44,"w":1440,"h":1310,"nm":"컴포지션 1","ddd":0,"assets":[{"id":"image_0","w":200,"h":192,"u":"images/","p":"img_0.png","e":0},{"id":"image_1","w":5760,"h":5240,"u":"images/","p":"img_1.jpg","e":0}],"layers":[{"ddd":0,"ind":1,"ty":2,"nm":"탄소.png","cl":"png","refId":"image_0","sr":1,"ks":{"o":{"a":1,"k":[{"i":{"x":[0.833],"y":[0.833]},"o":{"x":[0.167],"y":[0.167]},"t":23,"s":[0]},{"i":{"x":[0.833],"y":[0.833]},"o":{"x":[0.167],"y":[0.167]},"t":32,"s":[100]},{"t":39,"s":[0]}],"ix":11},"r":{"a":0,"k":0,"ix":10},"p":{"a":1,"k":[{"i":{"x":0.833,"y":0.833},"o":{"x":0.167,"y":0.167},"t":23,"s":[1117,1151.5,0],"to":[19.333,-12.167,0],"ti":[-19.667,26.833,0]},{"i":{"x":0.833,"y":0.833},"o":{"x":0.167,"y":0.167},"t":32,"s":[1233,1078.5,0],"to":[19.667,-26.833,0],"ti":[-0.333,14.667,0]},{"t":39,"s":[1235,990.5,0]}],"ix":2,"l":2},"a":{"a":0,"k":[100,96,0],"ix":1,"l":2},"s":{"a":0,"k":[25,25,100],"ix":6,"l":2}},"ao":0,"ip":23,"op":323,"st":23,"bm":0},{"ddd":0,"ind":2,"ty":2,"nm":"탄소.png","cl":"png","refId":"image_0","sr":1,"ks":{"o":{"a":1,"k":[{"i":{"x":[0.833],"y":[0.833]},"o":{"x":[0.167],"y":[0.167]},"t":18,"s":[0]},{"i":{"x":[0.833],"y":[0.833]},"o":{"x":[0.167],"y":[0.167]},"t":27,"s":[100]},{"t":34,"s":[0]}],"ix":11},"r":{"a":0,"k":0,"ix":10},"p":{"a":1,"k":[{"i":{"x":0.833,"y":0.833},"o":{"x":0.167,"y":0.167},"t":18,"s":[1056,1108.5,0],"to":[-3,-13.333,0],"ti":[13.333,25,0]},{"i":{"x":0.833,"y":0.833},"o":{"x":0.167,"y":0.167},"t":27,"s":[1038,1028.5,0],"to":[-13.333,-25,0],"ti":[10.333,11.667,0]},{"t":34,"s":[976,958.5,0]}],"ix":2,"l":2},"a":{"a":0,"k":[100,96,0],"ix":1,"l":2},"s":{"a":0,"k":[25,25,100],"ix":6,"l":2}},"ao":0,"ip":18,"op":318,"st":18,"bm":0},{"ddd":0,"ind":3,"ty":2,"nm":"탄소.png","cl":"png","refId":"image_0","sr":1,"ks":{"o":{"a":1,"k":[{"i":{"x":[0.833],"y":[0.833]},"o":{"x":[0.167],"y":[0.167]},"t":13,"s":[0]},{"i":{"x":[0.833],"y":[0.833]},"o":{"x":[0.167],"y":[0.167]},"t":22,"s":[100]},{"t":29,"s":[0]}],"ix":11},"r":{"a":0,"k":0,"ix":10},"p":{"a":1,"k":[{"i":{"x":0.833,"y":0.833},"o":{"x":0.167,"y":0.167},"t":13,"s":[1042,1139.5,0],"to":[-20.5,-1.333,0],"ti":[27.333,14.833,0]},{"i":{"x":0.833,"y":0.833},"o":{"x":0.167,"y":0.167},"t":22,"s":[919,1131.5,0],"to":[-27.333,-14.833,0],"ti":[6.833,13.5,0]},{"t":29,"s":[878,1050.5,0]}],"ix":2,"l":2},"a":{"a":0,"k":[100,96,0],"ix":1,"l":2},"s":{"a":0,"k":[25,25,100],"ix":6,"l":2}},"ao":0,"ip":13,"op":313,"st":13,"bm":0},{"ddd":0,"ind":4,"ty":4,"nm":"모양 레이어 1","sr":1,"ks":{"o":{"a":0,"k":100,"ix":11},"r":{"a":0,"k":0,"ix":10},"p":{"a":0,"k":[720,655,0],"ix":2,"l":2},"a":{"a":0,"k":[0,0,0],"ix":1,"l":2},"s":{"a":0,"k":[100,100,100],"ix":6,"l":2}},"ao":0,"shapes":[{"ty":"gr","it":[{"d":1,"ty":"el","s":{"a":0,"k":[138,138],"ix":2},"p":{"a":0,"k":[0,0],"ix":3},"nm":"타원 패스 1","mn":"ADBE Vector Shape - Ellipse","hd":false},{"ty":"tm","s":{"a":0,"k":0,"ix":1},"e":{"a":1,"k":[{"i":{"x":[0.833],"y":[0.833]},"o":{"x":[0.167],"y":[0.167]},"t":13,"s":[0]},{"t":21,"s":[100]}],"ix":2},"o":{"a":0,"k":0,"ix":3},"m":1,"ix":2,"nm":"패스 다듬어 자르기 1","mn":"ADBE Vector Filter - Trim","hd":false},{"ty":"st","c":{"a":0,"k":[1,1,1,1],"ix":3},"o":{"a":0,"k":100,"ix":4},"w":{"a":0,"k":2,"ix":5},"lc":1,"lj":1,"ml":4,"bm":0,"nm":"선 1","mn":"ADBE Vector Graphic - Stroke","hd":false},{"ty":"tr","p":{"a":0,"k":[357,471.5],"ix":2},"a":{"a":0,"k":[0,0],"ix":1},"s":{"a":0,"k":[100,100],"ix":3},"r":{"a":0,"k":0,"ix":6},"o":{"a":0,"k":100,"ix":7},"sk":{"a":0,"k":0,"ix":4},"sa":{"a":0,"k":0,"ix":5},"nm":"변형"}],"nm":"타원 1","np":4,"cix":2,"bm":0,"ix":1,"mn":"ADBE Vector Group","hd":false}],"ip":0,"op":300,"st":0,"bm":0},{"ddd":0,"ind":5,"ty":2,"nm":"탄소.png","cl":"png","refId":"image_0","sr":1,"ks":{"o":{"a":1,"k":[{"i":{"x":[0.833],"y":[0.833]},"o":{"x":[0.167],"y":[0.167]},"t":10,"s":[0]},{"i":{"x":[0.833],"y":[0.833]},"o":{"x":[0.167],"y":[0.167]},"t":19,"s":[100]},{"t":26,"s":[2]}],"ix":11},"r":{"a":0,"k":0,"ix":10},"p":{"a":1,"k":[{"i":{"x":0.833,"y":0.833},"o":{"x":0.167,"y":0.167},"t":10,"s":[529.946,1000.588,0],"to":[16,-12.167,0],"ti":[-21.667,26.167,0]},{"i":{"x":0.833,"y":0.833},"o":{"x":0.167,"y":0.167},"t":19,"s":[625.946,927.588,0],"to":[21.667,-26.167,0],"ti":[-5.667,14,0]},{"t":26,"s":[659.946,843.588,0]}],"ix":2,"l":2},"a":{"a":0,"k":[100,96,0],"ix":1,"l":2},"s":{"a":0,"k":[25,25,100],"ix":6,"l":2}},"ao":0,"ip":10,"op":310,"st":10,"bm":0},{"ddd":0,"ind":6,"ty":2,"nm":"탄소.png","cl":"png","refId":"image_0","sr":1,"ks":{"o":{"a":1,"k":[{"i":{"x":[0.833],"y":[0.833]},"o":{"x":[0.167],"y":[0.167]},"t":5,"s":[0]},{"i":{"x":[0.833],"y":[0.833]},"o":{"x":[0.167],"y":[0.167]},"t":14,"s":[100]},{"t":21,"s":[0]}],"ix":11},"r":{"a":0,"k":0,"ix":10},"p":{"a":1,"k":[{"i":{"x":0.833,"y":0.833},"o":{"x":0.167,"y":0.167},"t":5,"s":[333.902,883.187,0],"to":[-11.167,-9.167,0],"ti":[10.5,20.5,0]},{"i":{"x":0.833,"y":0.833},"o":{"x":0.167,"y":0.167},"t":14,"s":[266.902,828.187,0],"to":[-10.5,-20.5,0],"ti":[-0.667,11.333,0]},{"t":21,"s":[270.902,760.187,0]}],"ix":2,"l":2},"a":{"a":0,"k":[100,96,0],"ix":1,"l":2},"s":{"a":0,"k":[25,25,100],"ix":6,"l":2}},"ao":0,"ip":5,"op":305,"st":5,"bm":0},{"ddd":0,"ind":7,"ty":2,"nm":"탄소.png","cl":"png","refId":"image_0","sr":1,"ks":{"o":{"a":1,"k":[{"i":{"x":[0.833],"y":[0.833]},"o":{"x":[0.167],"y":[0.167]},"t":0,"s":[0]},{"i":{"x":[0.833],"y":[0.833]},"o":{"x":[0.167],"y":[0.167]},"t":9,"s":[100]},{"t":16,"s":[0]}],"ix":11},"r":{"a":0,"k":0,"ix":10},"p":{"a":1,"k":[{"i":{"x":0.833,"y":0.833},"o":{"x":0.167,"y":0.167},"t":0,"s":[305.5,960.5,0],"to":[-9.489,-10.635,0],"ti":[23.58,26.428,0]},{"i":{"x":0.833,"y":0.833},"o":{"x":0.167,"y":0.167},"t":9,"s":[235.281,912.25,0],"to":[-19.285,-21.614,0],"ti":[7.761,8.698,0]},{"t":16,"s":[202,844.5,0]}],"ix":2,"l":2},"a":{"a":0,"k":[100,96,0],"ix":1,"l":2},"s":{"a":0,"k":[25,25,100],"ix":6,"l":2}},"ao":0,"ip":0,"op":300,"st":0,"bm":0},{"ddd":0,"ind":8,"ty":2,"nm":"진짜배경.jpg","cl":"jpg","refId":"image_1","sr":1,"ks":{"o":{"a":0,"k":100,"ix":11},"r":{"a":0,"k":0,"ix":10},"p":{"a":0,"k":[720,655,0],"ix":2,"l":2},"a":{"a":0,"k":[2880,2620,0],"ix":1,"l":2},"s":{"a":0,"k":[25,25,100],"ix":6,"l":2}},"ao":0,"ip":0,"op":300,"st":0,"bm":0}],"markers":[]}